setup.py
LQTAgridPy.egg-info/PKG-INFO
LQTAgridPy.egg-info/SOURCES.txt
LQTAgridPy.egg-info/dependency_links.txt
LQTAgridPy.egg-info/entry_points.txt
LQTAgridPy.egg-info/requires.txt
LQTAgridPy.egg-info/top_level.txt
src/__init__.py
src/grid_generate.py
src/lqtagrid.py
src/matrix_generate.py
src/utils.py