Metadata-Version: 1.0
Name: LQTAgridPy
Version: 0.4
Summary: Python version of LQTAgrid
Home-page: https://github.com/rougeth/LQTAgridPy
Author: Marco Rougeth, Mário Sérgio
Author-email: marco@rougeth.com, sergio.mario_q@hotmail.com
License: UNKNOWN
Platform: UNKNOWN
